napari/__init__.py
napari/__init__.pyi
napari/__main__.py
napari/_check_numpy_version.py
napari/_event_loop.py
napari/_pydantic_compat.py
napari/_version.py
napari/conftest.py
napari/types.py
napari/view_layers.py
napari/view_layers.pyi
napari/viewer.py
napari/window.py
napari/_app_model/__init__.py
napari/_app_model/_app.py
napari/_app_model/utils.py
napari/_app_model/_tests/test_app.py
napari/_app_model/_tests/test_constants.py
napari/_app_model/_tests/test_context.py
napari/_app_model/actions/__init__.py
napari/_app_model/actions/_file.py
napari/_app_model/actions/_layerlist_context_actions.py
napari/_app_model/actions/_toggle_action.py
napari/_app_model/actions/_view.py
napari/_app_model/constants/__init__.py
napari/_app_model/constants/_menus.py
napari/_app_model/context/__init__.py
napari/_app_model/context/_context.py
napari/_app_model/context/_context_keys.py
napari/_app_model/context/_layerlist_context.py
napari/_qt/__init__.py
napari/_qt/qt_event_filters.py
napari/_qt/qt_event_loop.py
napari/_qt/qt_main_window.py
napari/_qt/qt_viewer.py
napari/_qt/qthreading.py
napari/_qt/utils.py
napari/_qt/_qapp_model/__init__.py
napari/_qt/_qapp_model/_menus.py
napari/_qt/_qapp_model/_tests/test_debug_menu.py
napari/_qt/_qapp_model/_tests/test_dummy_actions.py
napari/_qt/_qapp_model/_tests/test_file_menu.py
napari/_qt/_qapp_model/_tests/test_help_menu.py
napari/_qt/_qapp_model/_tests/test_layerlist_context_actions.py
napari/_qt/_qapp_model/_tests/test_plugins_menu.py
napari/_qt/_qapp_model/_tests/test_processors.py
napari/_qt/_qapp_model/_tests/test_qaction_layer.py
napari/_qt/_qapp_model/_tests/test_qapp_model_menus.py
napari/_qt/_qapp_model/_tests/test_qproviders.py
napari/_qt/_qapp_model/_tests/test_togglers.py
napari/_qt/_qapp_model/_tests/test_view_menu.py
napari/_qt/_qapp_model/_tests/test_window_menu.py
napari/_qt/_qapp_model/_tests/utils.py
napari/_qt/_qapp_model/injection/__init__.py
napari/_qt/_qapp_model/injection/_qprocessors.py
napari-0.6.5.dist-info/licenses/LICENSE
napari-0.6.5.dist-info/METADATA
napari-0.6.5.dist-info/WHEEL
napari-0.6.5.dist-info/entry_points.txt
napari-0.6.5.dist-info/top_level.txt
napari-0.6.5.dist-info/RECORD
