Metadata-Version: 2.4
Name: napari
Version: 0.6.5
Summary: n-dimensional array viewer in Python
Author-email: napari team <napari-steering-council@googlegroups.com>
License: BSD 3-Clause
Project-URL: Homepage, https://napari.org
Project-URL: Download, https://github.com/napari/napari
Project-URL: Bug Tracker, https://github.com/napari/napari/issues
Project-URL: Documentation, https://napari.org
Project-URL: Source Code, https://github.com/napari/napari
Classifier: Development Status :: 4 - Beta
Classifier: Environment :: X11 Applications :: Qt
Classifier: Framework :: napari
Classifier: Intended Audience :: Education
Classifier: Intended Audience :: Science/Research
Classifier: License :: OSI Approved :: BSD License
Classifier: Programming Language :: C
Classifier: Programming Language :: Python
Classifier: Programming Language :: Python :: 3 :: Only
Classifier: Programming Language :: Python :: 3.10
Classifier: Programming Language :: Python :: 3.11
Classifier: Programming Language :: Python :: 3.12
Classifier: Programming Language :: Python :: 3.13
Classifier: Topic :: Scientific/Engineering
Classifier: Topic :: Scientific/Engineering :: Visualization
Classifier: Topic :: Scientific/Engineering :: Information Analysis
Classifier: Topic :: Scientific/Engineering :: Bio-Informatics
Classifier: Topic :: Utilities
Classifier: Operating System :: Microsoft :: Windows
Classifier: Operating System :: POSIX
Classifier: Operating System :: Unix
Classifier: Operating System :: MacOS
Requires-Python: >=3.10
License-File: LICENSE
Requires-Dist: appdirs>=1.4.4
Requires-Dist: app-model<0.5.0,>=0.4.0
Requires-Dist: cachey>=0.2.1
Requires-Dist: certifi>=2018.1.18
Requires-Dist: dask[array]>=2021.10.0
Requires-Dist: imageio!=2.22.1,>=2.20
Requires-Dist: jsonschema>=3.2.0
Requires-Dist: lazy_loader>=0.3
Requires-Dist: magicgui>=0.7.0
Requires-Dist: napari-console>=0.1.1
Requires-Dist: napari-plugin-engine>=0.1.9
Requires-Dist: napari-svg>=0.1.8
Requires-Dist: npe2>=0.7.9
Requires-Dist: numpy>=1.24.2
Requires-Dist: numpydoc>=1.0.0
Requires-Dist: pandas>=1.3.3
Requires-Dist: Pillow>=9.0
Requires-Dist: pint>=0.17
Requires-Dist: psutil>=5.9.0
Requires-Dist: psygnal>=0.14.2
Requires-Dist: pydantic>=2.2.0
Requires-Dist: pygments>=2.6.0
Requires-Dist: PyOpenGL>=3.1.5
Requires-Dist: pywin32; platform_system == "Windows"
Requires-Dist: PyYAML>=6.0
Requires-Dist: qtpy>=2.3.1
Requires-Dist: scikit-image[data]>=0.19.1
Requires-Dist: scipy>=1.10.1
Requires-Dist: superqt>=0.7.4
Requires-Dist: tifffile>=2022.7.28
Requires-Dist: toolz>=0.11.0
Requires-Dist: tqdm>=4.56.0
Requires-Dist: typing_extensions>=4.12
Requires-Dist: vispy<0.16,>=0.15.2
Requires-Dist: wrapt>=1.13.3
Provides-Extra: pyside2
Requires-Dist: PySide2>=5.15.1; (python_version < "3.11" and platform_machine != "arm64") and extra == "pyside2"
Provides-Extra: pyside6
Requires-Dist: PySide6>6.7; extra == "pyside6"
Provides-Extra: pyqt6
Requires-Dist: PyQt6>6.5; extra == "pyqt6"
Requires-Dist: PyQt6!=6.6.1; platform_system == "Darwin" and extra == "pyqt6"
Provides-Extra: pyside
Requires-Dist: napari[pyside2]; extra == "pyside"
Provides-Extra: pyqt5
Requires-Dist: PyQt5>=5.15.8; extra == "pyqt5"
Requires-Dist: pyqt5-qt5<=5.15.2; sys_platform == "Windows" and extra == "pyqt5"
Provides-Extra: pyqt
Requires-Dist: napari[pyqt5]; extra == "pyqt"
Provides-Extra: qt
Requires-Dist: napari[pyqt]; extra == "qt"
Provides-Extra: all
Requires-Dist: napari[optional,pyqt]; extra == "all"
Provides-Extra: optional-base
Requires-Dist: zarr>=2.12.0; extra == "optional-base"
Requires-Dist: aiohttp; extra == "optional-base"
Requires-Dist: napari-plugin-manager<0.2.0,>=0.1.3; extra == "optional-base"
Provides-Extra: optional-numba
Requires-Dist: numba>=0.57.1; extra == "optional-numba"
Provides-Extra: optional
Requires-Dist: napari[bermuda,optional-base,optional-numba]; extra == "optional"
Requires-Dist: triangle; extra == "optional"
Provides-Extra: bermuda
Requires-Dist: bermuda>=0.1.5; extra == "bermuda"
Provides-Extra: partsegcore
Requires-Dist: PartSegCore-compiled-backend>=0.15.11; extra == "partsegcore"
Provides-Extra: all-optional
Requires-Dist: napari[optional,partsegcore]; extra == "all-optional"
Provides-Extra: testing
Requires-Dist: napari[gallery]; extra == "testing"
Requires-Dist: babel>=2.9.0; extra == "testing"
Requires-Dist: fsspec>=2023.10.0; extra == "testing"
Requires-Dist: hypothesis>=6.8.0; extra == "testing"
Requires-Dist: lxml[html_clean]>5; extra == "testing"
Requires-Dist: matplotlib>=3.6.1; extra == "testing"
Requires-Dist: pooch>=1.6.0; extra == "testing"
Requires-Dist: coverage>7; extra == "testing"
Requires-Dist: docstring_parser>=0.15; extra == "testing"
Requires-Dist: pretend>=1.0.9; extra == "testing"
Requires-Dist: pyautogui>=0.9.54; extra == "testing"
Requires-Dist: pytest-qt>=4.4.0; python_version > "3.10" and extra == "testing"
Requires-Dist: pytest-qt==4.4.0; python_version <= "3.10" and extra == "testing"
Requires-Dist: pytest-pretty>=1.1.0; extra == "testing"
Requires-Dist: pytest>=8.3.5; extra == "testing"
Requires-Dist: pytest-rerunfailures>=15.1; extra == "testing"
Requires-Dist: tensorstore>=0.1.32; extra == "testing"
Requires-Dist: virtualenv>=20.17; extra == "testing"
Requires-Dist: xarray>=0.16.2; extra == "testing"
Requires-Dist: IPython>=7.25.0; extra == "testing"
Requires-Dist: qtconsole>=4.5.1; extra == "testing"
Requires-Dist: rich>=12.0.0; extra == "testing"
Requires-Dist: napari[optional-base]; extra == "testing"
Provides-Extra: testing-extra
Requires-Dist: torch>=1.10.2; extra == "testing-extra"
Provides-Extra: gallery
Requires-Dist: glasbey; extra == "gallery"
Requires-Dist: zarr; extra == "gallery"
Requires-Dist: dask[array,distributed]; extra == "gallery"
Requires-Dist: matplotlib; extra == "gallery"
Requires-Dist: pooch; extra == "gallery"
Requires-Dist: nilearn; extra == "gallery"
Requires-Dist: xarray; extra == "gallery"
Requires-Dist: h5netcdf; extra == "gallery"
Requires-Dist: meshio; extra == "gallery"
Provides-Extra: docs
Requires-Dist: napari[gallery]; extra == "docs"
Requires-Dist: sphinx<8; extra == "docs"
Requires-Dist: sphinx-autobuild; extra == "docs"
Requires-Dist: sphinx-tabs; extra == "docs"
Requires-Dist: sphinx-tags; extra == "docs"
Requires-Dist: sphinx-design; extra == "docs"
Requires-Dist: sphinx-external-toc; extra == "docs"
Requires-Dist: sphinx-favicon>=1.0; extra == "docs"
Requires-Dist: sphinx-copybutton; extra == "docs"
Requires-Dist: sphinx-gallery; extra == "docs"
Requires-Dist: sphinx_autodoc_typehints==1.12.0; extra == "docs"
Requires-Dist: sphinxcontrib-mermaid>=1.0.0; extra == "docs"
Requires-Dist: sphinxext-opengraph[social-cards]; extra == "docs"
Requires-Dist: myst-nb; extra == "docs"
Requires-Dist: napari-sphinx-theme>=1.0.0; extra == "docs"
Requires-Dist: matplotlib; extra == "docs"
Requires-Dist: lxml[html_clean]>5; extra == "docs"
Requires-Dist: imageio-ffmpeg; extra == "docs"
Requires-Dist: pydeps; extra == "docs"
Requires-Dist: seedir; extra == "docs"
Requires-Dist: triangle; extra == "docs"
Requires-Dist: bermuda>=0.1.4; extra == "docs"
Requires-Dist: pytest; extra == "docs"
Requires-Dist: linkify-it-py; extra == "docs"
Provides-Extra: release
Requires-Dist: PyGithub>=1.46; extra == "release"
Requires-Dist: twine>=3.1.1; extra == "release"
Requires-Dist: gitpython>=3.1.0; extra == "release"
Requires-Dist: requests-cache>=0.9.2; extra == "release"
Provides-Extra: dev
Requires-Dist: ruff; extra == "dev"
Requires-Dist: check-manifest>=0.42; extra == "dev"
Requires-Dist: pre-commit>=2.9.0; extra == "dev"
Requires-Dist: pydantic; extra == "dev"
Requires-Dist: tox; extra == "dev"
Requires-Dist: tox-min-req; extra == "dev"
Requires-Dist: napari[testing]; extra == "dev"
Provides-Extra: build
Requires-Dist: ruff; extra == "build"
Requires-Dist: pyqt5; extra == "build"
Dynamic: license-file
